panda/__init__.py
panda/ads/__init__.py
panda_ads-0.0.1.dist-info/LICENSE
panda_ads-0.0.1.dist-info/METADATA
panda_ads-0.0.1.dist-info/WHEEL
panda_ads-0.0.1.dist-info/top_level.txt
panda_ads-0.0.1.dist-info/RECORD
